staliro/__about__.py
staliro/__init__.py
staliro/cost_func.py
staliro/models.py
staliro/optimizers.py
staliro/options.py
staliro/py.typed
staliro/signals.py
staliro/tests.py
staliro/specifications/__init__.py
staliro/specifications/rtamt.py
staliro/specifications/specification.py
psy_taliro-1.0.0.dist-info/METADATA
psy_taliro-1.0.0.dist-info/WHEEL
psy_taliro-1.0.0.dist-info/licenses/LICENSE
psy_taliro-1.0.0.dist-info/RECORD
