Metadata-Version: 2.1
Name: psy-taliro
Version: 1.0.0
Summary: Search-based test generation framework
Project-URL: Documentation, https://github.com/cpslab-asu/psy-taliro#readme
Project-URL: Issues, https://github.com/cpslab-asu/psy-taliro/issues
Project-URL: Source, https://github.com/cpslab-asu/psy-taliro
Author-email: Quinn Thibeault <quinn.thibeault@asu.com>
License-File: LICENSE
Classifier: Development Status :: 4 - Beta
Classifier: Programming Language :: Python
Classifier: Programming Language :: Python :: 3.9
Classifier: Programming Language :: Python :: 3.10
Classifier: Programming Language :: Python :: 3.11
Classifier: Programming Language :: Python :: 3.12
Classifier: Programming Language :: Python :: Implementation :: CPython
Requires-Python: >=3.9
Requires-Dist: attrs~=23.2
Requires-Dist: matplotlib~=3.8
Requires-Dist: numpy~=1.26
Requires-Dist: pathos~=0.3
Requires-Dist: rtamt~=0.3
Requires-Dist: scipy~=1.11
Requires-Dist: sortedcontainers~=2.4
Requires-Dist: typing-extensions~=4.9
